[{"pk": 2, "model": "contas.historico", "fields": {"descricao": "Alguel", "usuario": 1}}, {"pk": 1, "model": "contas.historico", "fields": {"descricao": "Cartao Evelyn", "usuario": 1}}, {"pk": 5, "model": "contas.historico", "fields": {"descricao": "Compras de pao.", "usuario": 7}}, {"pk": 3, "model": "contas.historico", "fields": {"descricao": "Notebook", "usuario": 1}}, {"pk": 4, "model": "contas.historico", "fields": {"descricao": "Notebook", "usuario": 1}}, {"pk": 1, "model": "contas.pessoa", "fields": {"usuario": 2, "telefone": "00000000", "nome": "Evelyn de Melo"}}, {"pk": 5, "model": "contas.pessoa", "fields": {"usuario": 6, "telefone": "132", "nome": "Madrinha"}}, {"pk": 4, "model": "contas.pessoa", "fields": {"usuario": 5, "telefone": "3123", "nome": "M\u00e3e"}}, {"pk": 6, "model": "contas.pessoa", "fields": {"usuario": 7, "telefone": "123123", "nome": "Padaria"}}, {"pk": 3, "model": "contas.pessoa", "fields": {"usuario": 4, "telefone": "123", "nome": "Paulo"}}, {"pk": 2, "model": "contas.pessoa", "fields": {"usuario": 3, "telefone": "123123", "nome": "Tiago"}}, {"pk": 15, "model": "contas.conta", "fields": {"operacao": "d", "status": "a", "data_pagamento": null, "usuario": 8, "data_vencimento": "2013-05-14", "valor": "133.00", "historico": 1, "pessoa": 1, "descricao": ""}}, {"pk": 15, "model": "contas.contapagar", "fields": {}}]